Workbook

Sheet Summary
A1: FTLR Fitness: revenue summary
A3: Fiverr fee rate | B3: 0.2 | C3: Check your own Fiverr dashboard and change this if your fee differs.
A4: Your target (gross) | B4: 5000
A5: Care plan per month | B5: 199
A6: Care plan months in first 90 days | B6: 3
A7: Planned one time total (gross) | B7: =Roadmap!H21
A8: Planned one time total (net after fee) | B8: =Roadmap!J21
A9: Care plan over the period (gross) | B9: =B5*B6
A10: Planned total including care plan (gross) | B10: =B7+B9
A11: Gap to target (gross, one time only) | B11: =B4-B7
A12: Paid so far (gross) | B12: =SUMIF(Roadmap!K5:K20,"Paid",Roadmap!H5:H20)
A13: Accepted or delivered, not yet paid | B13: =SUMIF(Roadmap!K5:K20,"Accepted",Roadmap!H5:H20)+SUMIF(Roadmap!K5:K20,"Delivered",Roadmap!H5:H20)
A14: Offered, waiting for her yes | B14: =SUMIF(Roadmap!K5:K20,"Offered",Roadmap!H5:H20)
A15: Progress to target | B15: =B12/B4
A17: By phase
A18: Launch ready | B18: =SUMIF(Roadmap!B5:B20,A18,Roadmap!H5:H20)
A19: Launch week | B19: =SUMIF(Roadmap!B5:B20,A19,Roadmap!H5:H20)
A20: Build the habit | B20: =SUMIF(Roadmap!B5:B20,A20,Roadmap!H5:H20)
A21: Grow | B21: =SUMIF(Roadmap!B5:B20,A21,Roadmap!H5:H20)
A23: Cash by month (gross, if every item is accepted)
A24: Oct 2026 | B24: =SUMIF(Roadmap!G5:G20,A24,Roadmap!H5:H20)
A25: Nov 2026 | B25: =SUMIF(Roadmap!G5:G20,A25,Roadmap!H5:H20)
A26: Dec 2026 | B26: =SUMIF(Roadmap!G5:G20,A26,Roadmap!H5:H20)
A27: Jan 2027 | B27: =SUMIF(Roadmap!G5:G20,A27,Roadmap!H5:H20)
A29: Check: months add up to total | B29: =IF(SUM(B24:B27)=B7,"OK","CHECK")
A31: Rules
A32: 1. One open offer at a time. Deliver, get her approval, then offer the next.
A33: 2. Every offer is a Fiverr custom offer. Never take payment outside Fiverr.
A34: 3. Start work only after the milestone is funded.
A35: 4. Each offer has a written scope. Anything extra is quoted separately.
A36: 5. Always lead with value: show a result first, then offer the next step.
A37: 6. If she says no or not now, mark Declined or move it later. Never push.

Sheet Roadmap
A1: FTLR Fitness: drip billing roadmap (internal, do not send)
A2: One small yes at a time. Send ONE Fiverr offer, deliver it, get approval, then offer the next. Blue cells are inputs you can change.
A4: # | B4: Phase | C4: Offer | D4: What she gets | E4: Why now (value to Leah) | F4: Offer it when | G4: Month | H4: Price (USD) | I4: Fiverr fee | J4: Net to you | K4: Status | L4: Date offered | M4: Notes
A5: 1 | B5: Launch ready | C5: App Store listing pack | D5: Name, subtitle, keywords, promotional text, checked and ready to paste | E5: Strangers find her app through the listing | F5: On the call or right after | G5: Oct 2026 | H5: 150 | I5: =H5*Summary!$B$3 | J5: =H5-I5 | K5: Not offered
A6: 2 | B6: Launch ready | C6: App Store screenshots, 5 designed | D6: Five captioned screenshots using her real screens, telling one story | E6: Screenshots decide who installs | F6: After the listing is approved | G6: Oct 2026 | H6: 250 | I6: =H6*Summary!$B$3 | J6: =H6-I6 | K6: Not offered
A7: 3 | B7: Launch ready | C7: Launch announcement pack | D7: Email, community post and pinned chat message, written in her voice | E7: Launch day needs words ready | F7: Before Nov 1 | G7: Oct 2026 | H7: 120 | I7: =H7*Summary!$B$3 | J7: =H7-I7 | K7: Not offered
A8: 4 | B8: Launch ready | C8: Welcome and 7 day message sequence | D8: Day 0, 1, 3, 7 and 14 messages written and set up | E8: First workout in 24 hours keeps members | F8: Launch week | G8: Nov 2026 | H8: 180 | I8: =H8*Summary!$B$3 | J8: =H8-I8 | K8: Not offered
A9: 5 | B9: Launch week | C9: Ratings prompt at happy moments | D9: Asks for a rating after a finished workout, never at a bad time | E9: Reviews build trust and ranking | F9: After first 20 members | G9: Nov 2026 | H9: 200 | I9: =H9*Summary!$B$3 | J9: =H9-I9 | K9: Not offered
A10: 6 | B10: Launch week | C10: Purchase flow polish | D10: Clearer progress and faster unlock after subscribing (today about 12 seconds) | E10: Waiting after paying feels risky | F10: After first real purchases | G10: Nov 2026 | H10: 180 | I10: =H10*Summary!$B$3 | J10: =H10-I10 | K10: Not offered
A11: 7 | B11: Build the habit | C11: Design quick pack | D11: Sign in and home screen: 3 improvements in her brand | E11: First impression, same calm look everywhere | F11: After launch week review | G11: Nov 2026 | H11: 350 | I11: =H11*Summary!$B$3 | J11: =H11-I11 | K11: Not offered
A12: 8 | B12: Build the habit | C12: Onboarding flow | D12: Goal choice, first workout nudge, welcome note from Leah | E12: Turns installs into active members | F12: After design quick pack | G12: Nov 2026 | H12: 450 | I12: =H12*Summary!$B$3 | J12: =H12-I12 | K12: Not offered
A13: 9 | B13: Build the habit | C13: Analytics dashboard | D13: Installs, active members, revenue and cancellations in one view | E13: Fix the biggest leak first | F13: 30 days after launch | G13: Dec 2026 | H13: 400 | I13: =H13*Summary!$B$3 | J13: =H13-I13 | K13: Not offered
A14: 10 | B14: Build the habit | C14: Workout reminders (push) | D14: Gentle reminders that bring members back | E14: Habit needs a nudge | F14: After onboarding is live | G14: Dec 2026 | H14: 550 | I14: =H14*Summary!$B$3 | J14: =H14-I14 | K14: Not offered
A15: 11 | B15: Grow | C15: Android, step 1: accounts and setup | D15: Google Play account, app record, billing set up | E15: Opens the other half of the market | F15: When Android demand is confirmed | G15: Dec 2026 | H15: 250 | I15: =H15*Summary!$B$3 | J15: =H15-I15 | K15: Not offered
A16: 12 | B16: Grow | C16: Android, step 2: build and billing | D16: Android app with the same subscriptions | E16: Same app, same plans | F16: After step 1 | G16: Dec 2026 | H16: 400 | I16: =H16*Summary!$B$3 | J16: =H16-I16 | K16: Not offered
... A20: 16 | B20: Grow | C20: Invite a friend system | D20: Referral link with a reward for both people | E20: Cheapest growth there is | F20: After retention is live | G20: Jan 2027 | H20: 450 | I20: =H20*Summary!$B$3 | J20: =H20-I20 | K20: Not offered
C21: TOTAL (one time) | H21: =SUM(H5:H20) | I21: =SUM(I5:I20) | J21: =SUM(J5:J20)

Sheet Messages
A1: Messages to send (adjust names and numbers)
A3: Situation | B3: Message
A4: Offer 1: Listing pack (after the call) | B4: Leah, thank you for your time today. The playbook gives you the structure. If you would like me to do the listing for you, I can write and check the App Store name, subtitle, keywords and promotional text so it is ready to paste. It is a small fixed job for $150, delivered in a short time, on Fiverr with payment protected. Shall I send the offer?
A5: Offer 2: Screenshots (after offer 1 is delivered) | B5: Leah, your listing is ready. The next thing that decides who installs is the screenshots. I can design five captioned screenshots using your real screens, telling the story we planned. It is $250 and I will need your screens or a quick screen recording. Want me to send the offer?
A6: Offer 3: Launch announcement pack | B6: Leah, launch is close. I can write your launch email, community post and pinned chat message in your voice so launch day is ready: $120. Shall I send it?
A7: Offer 4: Welcome sequence | B7: Leah, the first week decides if new members stay. I can write and set up your Day 0, 1, 3, 7 and 14 messages: $180. Want me to send the offer?
A8: Template: after any delivery | B8: Leah, here is [WHAT WAS DELIVERED]. How does it look? If you are happy, the next thing that helps most is [NEXT WIN], because [ONE SENTENCE OF VALUE]. It is $[PRICE]. Want me to send the offer, or would you rather wait?
A9: If she says not now | B9: Of course, no pressure. I will keep it on the list and check in after launch week. Congratulations again on the launch.
A10: If she asks for a discount | B10: I keep each job small and fixed so it stays easy. If the budget is tight, we can do the most important piece first and add the rest later.
